{
  "version": 1,
  "serviceConfiguration": {
    "apiName": "workbookac",
    "serviceName": "AppSync",
    "gqlSchemaPath": "/tmp/amplify-3b5cb66c-e95a-49bc-ad6a-76839fc9d9e7/amplify/backend/api/workbookac/schema.graphql",
    "defaultAuthType": {
      "mode": "API_KEY",
      "keyDescription": "api key description",
      "expirationTime": 30
    },
    "additionalAuthTypes": [
      {
        "mode": "AWS_IAM"
      }
    ],
    "conflictResolution": {
      "defaultResolutionStrategy": {
        "type": "AUTOMERGE"
      }
    }
  }
}